nekton/__init__.py
nekton/base.py
nekton/bins/dcm2nii
nekton/dcm2nii.py
nekton/externals/dcmqi/.git/HEAD
nekton/externals/dcmqi/.git/config
nekton/externals/dcmqi/.git/description
nekton/externals/dcmqi/.git/hooks/applypatch-msg.sample
nekton/externals/dcmqi/.git/hooks/commit-msg.sample
nekton/externals/dcmqi/.git/hooks/fsmonitor-watchman.sample
nekton/externals/dcmqi/.git/hooks/post-update.sample
nekton/externals/dcmqi/.git/hooks/pre-applypatch.sample
nekton/externals/dcmqi/.git/hooks/pre-commit.sample
nekton/externals/dcmqi/.git/hooks/pre-merge-commit.sample
nekton/externals/dcmqi/.git/hooks/pre-push.sample
nekton/externals/dcmqi/.git/hooks/pre-rebase.sample
nekton/externals/dcmqi/.git/hooks/pre-receive.sample
nekton/externals/dcmqi/.git/hooks/prepare-commit-msg.sample
nekton/externals/dcmqi/.git/hooks/push-to-checkout.sample
nekton/externals/dcmqi/.git/hooks/update.sample
nekton/externals/dcmqi/.git/index
nekton/externals/dcmqi/.git/info/exclude
nekton/externals/dcmqi/.git/logs/HEAD
nekton/externals/dcmqi/.git/logs/refs/heads/master
nekton/externals/dcmqi/.git/logs/refs/remotes/origin/HEAD
nekton/externals/dcmqi/.git/objects/pack/pack-385babdd9b32cdfb5ae9412a6cb1341c76e99d54.idx
nekton/externals/dcmqi/.git/objects/pack/pack-385babdd9b32cdfb5ae9412a6cb1341c76e99d54.pack
nekton/externals/dcmqi/.git/packed-refs
nekton/externals/dcmqi/.git/refs/heads/master
nekton/externals/dcmqi/.git/refs/remotes/origin/HEAD
nekton/externals/dcmqi/.github/workflows/cmake-linux.yml
nekton/externals/dcmqi/.github/workflows/cmake-macos.yml
nekton/externals/dcmqi/.github/workflows/cmake-win.yml
nekton/externals/dcmqi/.gitignore
nekton/externals/dcmqi/CMake/CTestCustom.cmake.in
nekton/externals/dcmqi/CMake/DCMQICPackOptions.cmake.in
nekton/externals/dcmqi/CMake/DCMQIConfig.cmake.in
nekton/externals/dcmqi/CMake/ExternalProjectDependency.cmake
nekton/externals/dcmqi/CMake/FindGit.cmake
nekton/externals/dcmqi/CMake/dcmqiBlockSetCMakeOSXVariables.cmake
nekton-0.2.6.dist-info/LICENSE
nekton-0.2.6.dist-info/METADATA
nekton-0.2.6.dist-info/WHEEL
nekton-0.2.6.dist-info/RECORD
