Metadata-Version: 2.1
Name: nekton
Version: 0.2.6
Summary: A python package for DICOM to NifTi and NifTi to DICOM-SEG and GSPS conversion
Home-page: https://github.com/deepc-health/nekton
License: MIT
Keywords: dicom,medical-imaging,nifti,dicom-seg,gsps
Author: a-parida12
Author-email: abhijeet@deepc.ai
Requires-Python: >=3.6.9,<4.0.0
Classifier: License :: OSI Approved :: MIT License
Classifier: Programming Language :: Python :: 3
Classifier: Programming Language :: Python :: 3.7
Classifier: Programming Language :: Python :: 3.8
Classifier: Programming Language :: Python :: 3.9
Classifier: Programming Language :: Python :: 3.10
Classifier: Programming Language :: Python :: 3.11
Requires-Dist: SimpleITK (>=2.1.1,<3.0.0)
Requires-Dist: nibabel (>=3.2.2,<4.0.0)
Requires-Dist: numpy (>=1.19.5,<2.0.0)
Requires-Dist: pydicom (>=2.3.0,<3.0.0)
Requires-Dist: pydicom-seg (==0.3.0)
Project-URL: Repository, https://github.com/deepc-health/nekton
